[
  {
    "id": "electroswap",
    "external": false,
    "title": "ElectroSwap",
    "logo": "https://electroswap.io/assets/images/boltpng-fdc0c443900d636867415c99d345df8a.png",
    "shortDescription": "The Future Of Decentralized Trading",
    "categories": ["Swaps","Liquid Staking","NFT"],
    "author": "electroswap",
    "url": "https://app.electroswap.io/swap",
    "description": "The Future Of Decentralized Trading On The Electroneum Network",
    "site": "https://electroswap.io/",
    "twitter": "https://x.com/electroswap_dex",
    "telegram": "",
    "github": "",
    "internalWallet": true,
    "priority": 7
  },
  {
    "id": "digidex",
    "external": true,
    "title": "DigiDEX",
    "logo": "https://assets.zyrosite.com/cdn-cgi/image/format=auto,w=262,h=254,fit=crop/dOqbj09QOoUOn5pe/2-squeaky-circle-logo-YX4P5XDE2ef8y8Or.png",
    "shortDescription": "DigiDEX is an open dex where developers can create Tokens and have the ability to trade on DigiDEX.me",
    "categories": ["Swaps"],
    "author": "digidex",
    "url": "https://swapdigidex.me/#/swap",
    "description": "DigiDEX is an open dex where developers can create Tokens and have the ability to trade on DigiDEX.me",
    "site": "https://digidex.me/",
    "twitter": "",
    "telegram": "https://t.me/DigitspinCrypto",
    "github": "",
    "internalWallet": false,
    "priority": 7
  }
]
